README.md
setup.cfg
setup.py
torch_intermediate_layer_getter/__init__.py
torch_intermediate_layer_getter/torch_intermediate_layer_getter.py
torch_intermediate_layer_getter.egg-info/PKG-INFO
torch_intermediate_layer_getter.egg-info/SOURCES.txt
torch_intermediate_layer_getter.egg-info/dependency_links.txt
torch_intermediate_layer_getter.egg-info/top_level.txt