Metadata-Version: 2.1
Name: torch-intermediate-layer-getter
Version: 0.1.post1
Summary: Simple easy to use module to get the intermediate results from chosen submodules
Home-page: https://github.com/sebamenabar/Pytorch-IntermediateLayerGetter
Author: Sebastian Amenabar
Author-email: amenabars@gmail.com
License: UNKNOWN
Platform: UNKNOWN
Classifier: License :: OSI Approved :: GNU General Public License v3 (GPLv3)
